<annotation>
	<folder>images</folder>
	<filename>064.jpg</filename>
	<path>D:\Desk\yolov5\yolov5-master\VOCdata\images\064.jpg</path>
	<source>
		<database>Unknown</database>
	</source>
	<size>
		<width>253</width>
		<height>199</height>
		<depth>3</depth>
	</size>
	<segmented>0</segmented>
	<object>
		<name>no-parking sign</name>
		<pose>Unspecified</pose>
		<truncated>0</truncated>
		<difficult>0</difficult>
		<bndbox>
			<xmin>144</xmin>
			<ymin>38</ymin>
			<xmax>168</xmax>
			<ymax>63</ymax>
		</bndbox>
	</object>
	<object>
		<name>car</name>
		<pose>Unspecified</pose>
		<truncated>0</truncated>
		<difficult>0</difficult>
		<bndbox>
			<xmin>107</xmin>
			<ymin>111</ymin>
			<xmax>208</xmax>
			<ymax>189</ymax>
		</bndbox>
	</object>
	<object>
		<name>car</name>
		<pose>Unspecified</pose>
		<truncated>0</truncated>
		<difficult>0</difficult>
		<bndbox>
			<xmin>8</xmin>
			<ymin>99</ymin>
			<xmax>29</xmax>
			<ymax>114</ymax>
		</bndbox>
	</object>
	<object>
		<name>car</name>
		<pose>Unspecified</pose>
		<truncated>0</truncated>
		<difficult>0</difficult>
		<bndbox>
			<xmin>30</xmin>
			<ymin>96</ymin>
			<xmax>43</xmax>
			<ymax>107</ymax>
		</bndbox>
	</object>
</annotation>
