<annotation>
	<folder>images</folder>
	<filename>070.jpg</filename>
	<path>D:\Desk\yolov5\yolov5-master\VOCdata\images\070.jpg</path>
	<source>
		<database>Unknown</database>
	</source>
	<size>
		<width>264</width>
		<height>191</height>
		<depth>3</depth>
	</size>
	<segmented>0</segmented>
	<object>
		<name>no-parking sign</name>
		<pose>Unspecified</pose>
		<truncated>0</truncated>
		<difficult>0</difficult>
		<bndbox>
			<xmin>198</xmin>
			<ymin>51</ymin>
			<xmax>223</xmax>
			<ymax>72</ymax>
		</bndbox>
	</object>
	<object>
		<name>car</name>
		<pose>Unspecified</pose>
		<truncated>0</truncated>
		<difficult>0</difficult>
		<bndbox>
			<xmin>133</xmin>
			<ymin>105</ymin>
			<xmax>178</xmax>
			<ymax>142</ymax>
		</bndbox>
	</object>
	<object>
		<name>car</name>
		<pose>Unspecified</pose>
		<truncated>0</truncated>
		<difficult>0</difficult>
		<bndbox>
			<xmin>73</xmin>
			<ymin>100</ymin>
			<xmax>94</xmax>
			<ymax>108</ymax>
		</bndbox>
	</object>
</annotation>
